marquee/__init__.py
marquee/_version.py
marquee/app.py
marquee_scroll-1.0.1.dist-info/DESCRIPTION.rst
marquee_scroll-1.0.1.dist-info/METADATA
marquee_scroll-1.0.1.dist-info/RECORD
marquee_scroll-1.0.1.dist-info/WHEEL
marquee_scroll-1.0.1.dist-info/entry_points.txt
marquee_scroll-1.0.1.dist-info/metadata.json
marquee_scroll-1.0.1.dist-info/top_level.txt
